tiny_render/__init__.py
tiny_render/render.py
tiny_render-0.2.0.dist-info/LICENSE
tiny_render-0.2.0.dist-info/METADATA
tiny_render-0.2.0.dist-info/WHEEL
tiny_render-0.2.0.dist-info/top_level.txt
tiny_render-0.2.0.dist-info/RECORD
