Metadata-Version: 2.1
Name: tiny-render
Version: 0.2.0
Summary: A tiny renderrer for replacing place holders in any text files
Home-page: https://github.com/zhongdai/tiny-render
Author: Zhong Dai
Author-email: zhongdai@gmail.com
License: UNKNOWN
Keywords: renderring template jinja2
Platform: UNKNOWN
Classifier: Development Status :: 2 - Pre-Alpha
Classifier: Intended Audience :: Developers
Classifier: Natural Language :: English
Classifier: Programming Language :: Python :: 3
Classifier: Programming Language :: Python :: 3.8
Classifier: Programming Language :: Python :: 3.9
Classifier: Programming Language :: Python :: 3.10
Requires-Python: >=3.7.3
Requires-Dist: Jinja2 (>=3.0.3)
